topsis_algo/topsis.py
topsis_Algorithm-2.0.0.dist-info/METADATA
topsis_Algorithm-2.0.0.dist-info/WHEEL
topsis_Algorithm-2.0.0.dist-info/entry_points.txt
topsis_Algorithm-2.0.0.dist-info/top_level.txt
topsis_Algorithm-2.0.0.dist-info/RECORD
