Metadata-Version: 2.1
Name: topsis-Algorithm
Version: 2.0.0
Summary: A Python package to get ranks of dataset using TOPSIS (UCS633).
Home-page: https://github.com/Pulkitg64/TOPSIS-in-Python
Author: Pulkit Gupta
Author-email: pulkitgupta64@gmail.com
License: UNKNOWN
Platform: UNKNOWN
Requires-Dist: requests
